dockerignore_find.py
dockerignore_find-0.1.0.dist-info/entry_points.txt
dockerignore_find-0.1.0.dist-info/WHEEL
dockerignore_find-0.1.0.dist-info/METADATA
dockerignore_find-0.1.0.dist-info/RECORD
