Metadata-Version: 2.1
Name: dockerignore-find
Version: 0.1.0
Summary: Helper with dockerignore files
License: MIT
Author: Martin Ortbauer
Author-email: mortbauer@gmail.com
Requires-Python: >=3.7,<4.0
Classifier: License :: OSI Approved :: MIT License
Classifier: Programming Language :: Python :: 3
Classifier: Programming Language :: Python :: 3.10
Classifier: Programming Language :: Python :: 3.7
Classifier: Programming Language :: Python :: 3.8
Classifier: Programming Language :: Python :: 3.9
